{"assets/sounds/death.wav":["assets/sounds/death.wav"],"assets/sounds/eat.wav":["assets/sounds/eat.wav"],"snake_asset/Tail_right.png":["snake_asset/Tail_right.png"],"snake_asset/body_bottomleft.png":["snake_asset/body_bottomleft.png"],"snake_asset/body_bottomright.png":["snake_asset/body_bottomright.png"],"snake_asset/body_horizontal.png":["snake_asset/body_horizontal.png"],"snake_asset/body_topleft.png":["snake_asset/body_topleft.png"],"snake_asset/body_topright.png":["snake_asset/body_topright.png"],"snake_asset/body_vertical.png":["snake_asset/body_vertical.png"],"snake_asset/grass.png":["snake_asset/grass.png"],"snake_asset/head_down.png":["snake_asset/head_down.png"],"snake_asset/head_left.png":["snake_asset/head_left.png"],"snake_asset/head_right.png":["snake_asset/head_right.png"],"snake_asset/head_up.png":["snake_asset/head_up.png"],"snake_asset/rabbit.png":["snake_asset/rabbit.png"],"snake_asset/tail_down.png":["snake_asset/tail_down.png"],"snake_asset/tail_left.png":["snake_asset/tail_left.png"],"snake_asset/tail_up.png":["snake_asset/tail_up.png"]}